[{"id":"1201071001","district_id":"1201071","name":"Tuhembuasi"},{"id":"1201071002","district_id":"1201071","name":"Hilibadalu"},{"id":"1201071003","district_id":"1201071","name":"Lauri"},{"id":"1201071004","district_id":"1201071","name":"Hilimbana"},{"id":"1201071005","district_id":"1201071","name":"Saetagaramba"},{"id":"1201071006","district_id":"1201071","name":"Sogaeadu"},{"id":"1201071007","district_id":"1201071","name":"Baruzo"},{"id":"1201071008","district_id":"1201071","name":"Tulumbaho"},{"id":"1201071009","district_id":"1201071","name":"Sihareo Sogaeadu"},{"id":"1201071010","district_id":"1201071","name":"Wea-Wea"},{"id":"1201071011","district_id":"1201071","name":"Sisarahili Sogeadu"}]