[{"id":"1403020001","district_id":"1403020","name":"Sanglar"},{"id":"1403020002","district_id":"1403020","name":"Pulau Kecil"},{"id":"1403020003","district_id":"1403020","name":"Pulau Kijang"},{"id":"1403020004","district_id":"1403020","name":"Sungai Undan"},{"id":"1403020005","district_id":"1403020","name":"Sungai Terab"},{"id":"1403020010","district_id":"1403020","name":"Seberang Sanglar"},{"id":"1403020011","district_id":"1403020","name":"Mekar Sari"},{"id":"1403020012","district_id":"1403020","name":"Seberang Pulau Kijang"},{"id":"1403020013","district_id":"1403020","name":"Sungai Asam"},{"id":"1403020014","district_id":"1403020","name":"Pulau Ruku"},{"id":"1403020015","district_id":"1403020","name":"Metro"},{"id":"1403020016","district_id":"1403020","name":"Madani"},{"id":"1403020017","district_id":"1403020","name":"Tanjung Labuh"},{"id":"1403020018","district_id":"1403020","name":"Sungai Mahang"}]