[{"id":"9411072001","district_id":"9411072","name":"Bunaluk"},{"id":"9411072002","district_id":"9411072","name":"Gereja Lama"},{"id":"9411072003","district_id":"9411072","name":"Anggalo"},{"id":"9411072004","district_id":"9411072","name":"Nanegeme"},{"id":"9411072005","district_id":"9411072","name":"Ponggoname"},{"id":"9411072006","district_id":"9411072","name":"Yunggwi"},{"id":"9411072007","district_id":"9411072","name":"Pernaluk"},{"id":"9411072008","district_id":"9411072","name":"Bime"},{"id":"9411072009","district_id":"9411072","name":"Wiyage"},{"id":"9411072010","district_id":"9411072","name":"Anggege"},{"id":"9411072011","district_id":"9411072","name":"Nuwi"},{"id":"9411072012","district_id":"9411072","name":"Piyabigimbut"},{"id":"9411072013","district_id":"9411072","name":"Kiburu"},{"id":"9411072014","district_id":"9411072","name":"Wanwi"},{"id":"9411072015","district_id":"9411072","name":"Gibume"},{"id":"9411072016","district_id":"9411072","name":"Naburage"},{"id":"9411072017","district_id":"9411072","name":"Anggagalo"}]