[{"id":"9107061","regency_id":"9107","name":"Klaso"},{"id":"9107062","regency_id":"9107","name":"Saengkeduk"},{"id":"9107100","regency_id":"9107","name":"Makbon"},{"id":"9107101","regency_id":"9107","name":"Klayili"},{"id":"9107110","regency_id":"9107","name":"Beraur"},{"id":"9107111","regency_id":"9107","name":"Klamono"},{"id":"9107112","regency_id":"9107","name":"Klabot"},{"id":"9107113","regency_id":"9107","name":"Klawak"},{"id":"9107114","regency_id":"9107","name":"Bagun"},{"id":"9107115","regency_id":"9107","name":"Klasafet"},{"id":"9107116","regency_id":"9107","name":"Malabotom"},{"id":"9107118","regency_id":"9107","name":"Botain"},{"id":"9107119","regency_id":"9107","name":"Konhir"},{"id":"9107120","regency_id":"9107","name":"Salawati"},{"id":"9107121","regency_id":"9107","name":"Mayamuk"},{"id":"9107122","regency_id":"9107","name":"Salawati Timur"},{"id":"9107123","regency_id":"9107","name":"Hobard"},{"id":"9107124","regency_id":"9107","name":"Buk"},{"id":"9107130","regency_id":"9107","name":"Seget"},{"id":"9107131","regency_id":"9107","name":"Segun"},{"id":"9107132","regency_id":"9107","name":"Salawati Selatan"},{"id":"9107133","regency_id":"9107","name":"Salawati Tengah"},{"id":"9107170","regency_id":"9107","name":"Aimas"},{"id":"9107171","regency_id":"9107","name":"Mariat"},{"id":"9107172","regency_id":"9107","name":"Sorong"},{"id":"9107180","regency_id":"9107","name":"Sayosa"},{"id":"9107181","regency_id":"9107","name":"Maudus"},{"id":"9107182","regency_id":"9107","name":"Wemak"},{"id":"9107183","regency_id":"9107","name":"Sayosa Timur"},{"id":"9107184","regency_id":"9107","name":"Sunook"}]